benchmark/__init__.py
skillbase/__init__.py
skillbase/trigger_detector.py
skillbase/util.py
skillbase-0.0.1.dist-info/LICENSE
skillbase-0.0.1.dist-info/METADATA
skillbase-0.0.1.dist-info/WHEEL
skillbase-0.0.1.dist-info/top_level.txt
skillbase-0.0.1.dist-info/RECORD
