Metadata-Version: 2.1
Name: skillbase
Version: 0.0.1
Summary: Skillbase python library
Author: SpaceGPT Team
Author-email: silveryfu@gmail.com
License: Apache License, Version 2.0
Requires-Python: >=3.8
License-File: LICENSE
Requires-Dist: openai
Requires-Dist: pyyaml
Requires-Dist: numpy
Requires-Dist: chromadb
Requires-Dist: langchain
Requires-Dist: tiktoken
Requires-Dist: unstructured
